bld/__init__.py
bld/__main__.py
bld/api_function.py
bld/deployer.py
bld/function.py
bld/queue.py
bld/sam.j2
bld/cli/__init__.py
bld/cli/cli.py
bld/cli/deploy/__init__.py
bld/cli/deploy/commands.py
bld/cli/invoke/__init__.py
bld/cli/invoke/commands.py
bld/cli/start_api/__init__.py
bld/cli/start_api/commands.py
better_lambda_deploy-0.8.5.dist-info/METADATA
better_lambda_deploy-0.8.5.dist-info/WHEEL
better_lambda_deploy-0.8.5.dist-info/entry_points.txt
better_lambda_deploy-0.8.5.dist-info/top_level.txt
better_lambda_deploy-0.8.5.dist-info/RECORD
