Metadata-Version: 2.1
Name: better-lambda-deploy
Version: 0.8.5
Summary: A better AWS Lambda deployment framework.
Author: Alex Wiss
Author-email: alexwisswolf@gmail.com
Requires-Python: >=3.7
Requires-Dist: click (>=7)
Requires-Dist: jinja2 (>=2.10)
Requires-Dist: aws-sam-cli (~=1.38.1)
Requires-Dist: aws-sam-translator (~=1.42.0)
Requires-Dist: boto3 (~=1.18.0)
Requires-Dist: botocore (==1.21.65)
Requires-Dist: pyrsistent (==0.15.0)
Requires-Dist: future (>=0.18)
Requires-Dist: markupsafe (>=1.1)
Requires-Dist: pyyaml (~=5.1)
Requires-Dist: simplejson (~=3.17)
Requires-Dist: jmespath (~=0.10.0)
Requires-Dist: python-dateutil (<2.8.1,~=2.6)
Requires-Dist: bottle (~=0.12.0)
Requires-Dist: pynamodb (>=5.0.0b4)
